radiko/__init__.py
radiko/client.py
radiko.py-3.0.8.dist-info/LICENSE
radiko.py-3.0.8.dist-info/METADATA
radiko.py-3.0.8.dist-info/WHEEL
radiko.py-3.0.8.dist-info/top_level.txt
radiko.py-3.0.8.dist-info/RECORD
