Metadata-Version: 2.1
Name: radiko.py
Version: 3.0.8
Summary: radiko rapper
Home-page: UNKNOWN
Author: akatonbo1011
Author-email: akatonbobook@gmail.com
License: UNKNOWN
Keywords: Radiko,radiko,radiko.py,Radiko.py
Platform: UNKNOWN
Classifier: Development Status :: 5 - Production/Stable
Classifier: Programming Language :: Python :: 3.8
Classifier: License :: OSI Approved :: BSD License
Requires-Dist: requests
Requires-Dist: m3u8
